{"Rep. McCarthy: Nobody in America wants Democrats' 'imaginary impeachment'": "https://video.foxnews.com/v/6087009616001/", "What the left won't tell you about immigration, climate change and Silicon Valley": "https://video.foxnews.com/v/6087009603001/", "Does Kavanaugh have a case to sue The New York Times?": "https://video.foxnews.com/v/6087008358001/", "Jackie Gingrich Cushman pens new book 'Our Broken America'": "https://video.foxnews.com/v/6087004230001/", "Deadline for North Carolina to redraw voting districts approaches": "https://video.foxnews.com/v/6086990097001/", "Kamala Harris says she supports a mandatory buyback on 'assault weapons'": "/politics/kamala-harris-says-she-supports-a-mandatory-buyback-on-assault-weapons", "Breaking down the 10 counties that will decide the 2020 election": "https://video.foxnews.com/v/6086976284001/", "Trump blasts Democrats' Green New Deal at New Mexico rally": "https://video.foxnews.com/v/6086981458001/", "Durbin asked about prospects of Kavanaugh impeachment, says \u2018get real\u2019": "/politics/durbin-kavanaugh-impeachment", "US shares info with Saudi Arabia that blames Iran for oil field attack: report": "/politics/us-informs-saudi-arabia-that-iran-launched-oil-field-attack-report", "Kamala Harris doubles down on call for Kavanaugh's impeachment: The allegations are 'credible'": "/politics/kamala-harris-doubles-down-on-call-for-kavanaughs-impeachment-the-allegations-are-credible", "New York Times faces intense scrutiny over Kavanaugh article": "https://video.foxnews.com/v/6086901121001/", "President Trump courts voters in New Mexico": "https://video.foxnews.com/v/6086906728001/", "Sen. Tillis on New York Times Kavanaugh report": "https://video.foxnews.com/v/6086901917001/", "New York Times issues correction on Kavanugh story": "https://video.foxnews.com/v/6086901911001/"}